ravenpy/__init__.py
ravenpy/_raven.py
ravenpy/ravenpy.py
ravenpy/cli/__init__.py
ravenpy/cli/aggregate_forcings_to_hrus.py
ravenpy/cli/collect_subbasins_upstream_of_gauge.py
ravenpy/cli/generate_grid_weights.py
ravenpy/cli/generate_hrus_from_routing_product.py
ravenpy/config/__init__.py
ravenpy/config/base.py
ravenpy/config/commands.py
ravenpy/config/conventions.py
ravenpy/config/defaults.py
ravenpy/config/options.py
ravenpy/config/parsers.py
ravenpy/config/processes.py
ravenpy/config/rvs.py
ravenpy/config/utils.py
ravenpy/config/emulators/__init__.py
ravenpy/config/emulators/blended.py
ravenpy/config/emulators/canadianshield.py
ravenpy/config/emulators/gr4jcn.py
ravenpy/config/emulators/hbvec.py
ravenpy/config/emulators/hmets.py
ravenpy/config/emulators/hypr.py
ravenpy/config/emulators/mohyse.py
ravenpy/config/emulators/routing.py
ravenpy/config/emulators/sacsma.py
ravenpy/data/hydrobasins_domains/hybas_lake_ar_lev01_v1c.zip
ravenpy/data/hydrobasins_domains/hybas_lake_na_lev01_v1c.zip
ravenpy/data/regionalisation/GR4JCN_parameters.csv
ravenpy/data/regionalisation/HMETS_parameters.csv
ravenpy/data/regionalisation/MOHYSE_parameters.csv
ravenpy/data/regionalisation/gauged_catchment_properties.csv
ravenpy/extractors/__init__.py
ravenpy/extractors/forecasts.py
ravenpy/extractors/routing_product.py
ravenpy/testing/__init__.py
ravenpy/testing/helpers.py
ravenpy/testing/registry.txt
ravenpy/testing/utils.py
ravenpy/utilities/__init__.py
ravenpy/utilities/analysis.py
ravenpy/utilities/calibration.py
ravenpy/utilities/checks.py
ravenpy/utilities/coords.py
ravenpy/utilities/forecasting.py
ravenpy/utilities/geo.py
ravenpy/utilities/geoserver.py
ravenpy/utilities/graphs.py
ravenpy/utilities/io.py
ravenpy/utilities/mk_test.py
ravenpy/utilities/nb_graphs.py
ravenpy/utilities/publishing.py
ravenpy/utilities/ravenio.py
ravenpy/utilities/regionalization.py
ravenpy-0.19.1.dist-info/entry_points.txt
ravenpy-0.19.1.dist-info/licenses/LICENSE
ravenpy-0.19.1.dist-info/WHEEL
ravenpy-0.19.1.dist-info/METADATA
ravenpy-0.19.1.dist-info/RECORD
