Metadata-Version: 2.4
Name: ravenpy
Version: 0.19.1
Summary: A Python wrapper for configuring and running the hydrologic modelling framework Raven.
Keywords: raven,raven-hydro,hydrology,gis,analysis,modelling
Author-email: David Huard <huard.david@ouranos.ca>, Richard Arsenault <Richard.Arsenault@etsmtl.ca>
Maintainer-email: Trevor James Smith <smith.trevorj@ouranos.ca>
Requires-Python: >=3.10.0
Classifier: Development Status :: 4 - Beta
Classifier: Intended Audience :: Developers
Classifier: Intended Audience :: Education
Classifier: Intended Audience :: Science/Research
Classifier: License :: OSI Approved :: MIT License
Classifier: Natural Language :: English
Classifier: Operating System :: OS Independent
Classifier: Programming Language :: Python :: 3 :: Only
Classifier: Programming Language :: Python :: 3.10
Classifier: Programming Language :: Python :: 3.11
Classifier: Programming Language :: Python :: 3.12
Classifier: Programming Language :: Python :: 3.13
Classifier: Programming Language :: Python :: Implementation :: CPython
Classifier: Topic :: Scientific/Engineering :: Atmospheric Science
Classifier: Topic :: Scientific/Engineering :: GIS
Classifier: Topic :: Scientific/Engineering :: Hydrology
Classifier: Typing :: Typed
License-File: LICENSE
Requires-Dist: cftime >=1.4.1
Requires-Dist: cf-xarray >=0.9.3
Requires-Dist: click >=8.2.0
Requires-Dist: climpred >=2.4.0
Requires-Dist: dask >=2024.8.1
Requires-Dist: h5netcdf >=1.3.0
Requires-Dist: haversine >=2.8.0
Requires-Dist: matplotlib >=3.6.0
Requires-Dist: numpy >=1.25.0
Requires-Dist: owslib >=0.29.1
Requires-Dist: pandas >=2.2.0
Requires-Dist: pint >=0.24.4
Requires-Dist: pydantic >=2.11
Requires-Dist: pydap >=3.4.0,<3.5.5
Requires-Dist: pymbolic >=2024.2
Requires-Dist: scipy >=1.11.0
Requires-Dist: spotpy >=1.6.1
Requires-Dist: statsmodels >=0.14.2
Requires-Dist: typing-extensions
Requires-Dist: xarray >=2023.11.0,!=2024.10.0
Requires-Dist: xclim >=0.57.0
Requires-Dist: xsdba >=0.4.0
Requires-Dist: xskillscore
Requires-Dist: ravenpy[dev] ; extra == "all"
Requires-Dist: ravenpy[docs] ; extra == "all"
Requires-Dist: ravenpy[gis] ; extra == "all"
Requires-Dist: ravenpy[raven-hydro] ; extra == "all"
Requires-Dist: black ==25.1.0 ; extra == "dev"
Requires-Dist: blackdoc ==0.4.1 ; extra == "dev"
Requires-Dist: bump-my-version >=1.2.0 ; extra == "dev"
Requires-Dist: coverage >=7.5.0 ; extra == "dev"
Requires-Dist: filelock >=3.14.0 ; extra == "dev"
Requires-Dist: flake8 >=7.2.0 ; extra == "dev"
Requires-Dist: flake8-rst-docstrings >=0.3.0 ; extra == "dev"
Requires-Dist: flit >=3.11.0,<4.0 ; extra == "dev"
Requires-Dist: holoviews ; extra == "dev"
Requires-Dist: hvplot ; extra == "dev"
Requires-Dist: mypy >=1.14.1 ; extra == "dev"
Requires-Dist: nbval ; extra == "dev"
Requires-Dist: numpydoc >=1.8.0 ; extra == "dev"
Requires-Dist: pip >=25.0 ; extra == "dev"
Requires-Dist: pooch >=1.8.0 ; extra == "dev"
Requires-Dist: pre-commit >=3.5.0 ; extra == "dev"
Requires-Dist: pylint >=3.3.0 ; extra == "dev"
Requires-Dist: pytest >=8.3.2 ; extra == "dev"
Requires-Dist: pytest-cov >=5.0.0 ; extra == "dev"
Requires-Dist: pytest-xdist >=3.2.0 ; extra == "dev"
Requires-Dist: ruff >=0.12.0 ; extra == "dev"
Requires-Dist: tox >=4.26.0 ; extra == "dev"
Requires-Dist: watchdog >=4.0.0 ; extra == "dev"
Requires-Dist: autodoc-pydantic >=2.1.0 ; extra == "docs"
Requires-Dist: birdhouse-birdy ; extra == "docs"
Requires-Dist: cairosvg >=2.6.0 ; extra == "docs"
Requires-Dist: cartopy >=0.23.0 ; extra == "docs"
Requires-Dist: clisops >=0.16.1 ; extra == "docs"
Requires-Dist: gcsfs ; extra == "docs"
Requires-Dist: intake <2.0 ; extra == "docs"
Requires-Dist: intake-esm >=2023.07.07 ; extra == "docs"
Requires-Dist: intake-xarray <2.0 ; extra == "docs"
Requires-Dist: ipykernel ; extra == "docs"
Requires-Dist: ipyleaflet ; extra == "docs"
Requires-Dist: ipython >=8.5.0 ; extra == "docs"
Requires-Dist: ipywidgets ; extra == "docs"
Requires-Dist: jupyter-cache ; extra == "docs"
Requires-Dist: jupyter_client ; extra == "docs"
Requires-Dist: jupytext ; extra == "docs"
Requires-Dist: matplotlib >=3.6.0 ; extra == "docs"
Requires-Dist: myst_nb ; extra == "docs"
Requires-Dist: nbsphinx >=0.9.5 ; extra == "docs"
Requires-Dist: pymetalink >=6.5.2 ; extra == "docs"
Requires-Dist: s3fs ; extra == "docs"
Requires-Dist: salib ; extra == "docs"
Requires-Dist: sphinx >=7.1.0 ; extra == "docs"
Requires-Dist: sphinx-click ; extra == "docs"
Requires-Dist: sphinx-codeautolink ; extra == "docs"
Requires-Dist: sphinx-copybutton ; extra == "docs"
Requires-Dist: sphinx-rtd-theme >=1.0 ; extra == "docs"
Requires-Dist: sphinxcontrib-svg2pdfconverter >=1.2.3 ; extra == "docs"
Requires-Dist: xesmf ; extra == "docs"
Requires-Dist: zarr >=2.10.0,<3.0 ; extra == "docs"
Requires-Dist: affine >=2.4.0 ; extra == "gis"
Requires-Dist: fiona >=1.9 ; extra == "gis"
Requires-Dist: geopandas >=1.0 ; extra == "gis"
Requires-Dist: gdal >=3.1 ; extra == "gis"
Requires-Dist: lxml ; extra == "gis"
Requires-Dist: netcdf4 >=1.7.2 ; extra == "gis"
Requires-Dist: pyproj >=3.3.0 ; extra == "gis"
Requires-Dist: rasterio ; extra == "gis"
Requires-Dist: rioxarray ; extra == "gis"
Requires-Dist: setuptools >=71.0 ; extra == "gis"
Requires-Dist: shapely >=2.0 ; extra == "gis"
Requires-Dist: raven-hydro >=0.4.0,<1.0 ; extra == "raven-hydro"
Project-URL: About CSHS-CWRA, https://cwra.org/en/
Project-URL: About Ouranos, https://ouranos.ca/en/
Project-URL: Changelog, https://ravenpy.readthedocs.io/en/latest/changelog.html
Project-URL: Homepage, https://ravenpy.readthedocs.io
Project-URL: Issue tracker, https://github.com/CSHS-CWRA/RavenPy/issues
Project-URL: Source, https://github.com/CSHS-CWRA/RavenPy
Provides-Extra: all
Provides-Extra: dev
Provides-Extra: docs
Provides-Extra: gis
Provides-Extra: raven-hydro
